[
    {
        "cr": "[CR]",
        "name": "[NAME]",
        "alignment": "[N]",
        "senses": "[]",
        "size": "[SIZE]",
        "race": "[RACE]",
        "type": "[TYPE]",
        "initiative": 10,
        "classes": [
            "Wizard (Abjurer)",
            "Wizard (Abjurer)",
            "Wizard (Abjurer)",
            "Wizard (Abjurer)",
            "Wizard (Abjurer)"
        ],
        "defense": {
            "dr": "",
            "immune": "",
            "resist": "acid, cold, electricity, fire, or sonic 5",
            "sr": ""
        },
        "offense": {
            "speed": "30 ft.",
            "space": "5 ft.",
            "reach": "5 ft.",
            "attacks": {
                "melee": [],
                "ranged": [],
                "special": []
            },
            "slas": [],
            "spells": [
                {
                    "class": "Cleric",
                    "type": "Prepared",
                    "casterLevel": 12,
                    "concentrationBonus": 0,
                    "stat": "wis",
                    "spellResistance": 12,
                    "otherText": {
                        "heading": "Domains",
                        "text": "Charm, Trickery"
                    },
                    "list": [
                    [
                        "Geas/Quest||type:D",
                        "Greater Dispel Magic",
                        "Word Of Recall"
                    ],
                    [
                        "Breath of Life",
                        "Charm Monster||type:D",
                        "Greater Command",
                        "Slay Living",
                        "Spell Resistance"
                    ],
                    [
                        "Chaos Hammer",
                        "Cure Serious Wounds",
                        "Discern Lies",
                        "Heroism||type:D",
                        "Poison"
                    ],
                    [
                        "Invisibility Purge",
                        "Magic Vestment",
                        "Prayer",
                        "Protection from Energy",
                        "Searing Light",
                        "Suggestion||type:D"
                    ],
                    [
                        "Calm Emotions",
                        "Delay Poison",
                        "Enthrall",
                        "Hold Person||count:2",
                        "Invisibility||type:D"
                    ],
                    [
                        "Charm Person||type:D",
                        "Cure Light Wounds||count:2",
                        "Entropic Shield",
                        "Hide from Undead",
                        "Obscuring Mist",
                        "Remove Fear"
                    ],
                    [
                        "Detect Magic",
                        "Light",
                        "Mending",
                        "Purify Food and Drink"
                    ]
                    ]
                },
                {
                    "class": "Sorcerer",
                    "type": "Known",
                    "casterLevel": 8,
                    "concentrationBonus": 0,
                    "stat": "cha",
                    "spellResistance": 8,
                    "otherText": {
                        "heading": "Bloodline",
                        "text": "Fey"
                    },
                    "perDay": [
                        4,
                        6,
                        7,
                        7
                    ],
                    "list": [
                        [
                            "Phantasmal Killer"
                        ],
                        [
                            "Deep Slumber",
                            "Major Image",
                            "Suggestion"
                        ],
                        [
                            "Hideous Laughter",
                            "Hypnotic Pattern",
                            "Mirror Image",
                            "Scorching Ray"
                        ],
                        [
                            "Charm Person",
                            "Color Spray",
                            "Entangle",
                            "Magic Missile",
                            "Shield",
                            "Ventriloquism"
                        ],
                        [
                            "Daze",
                            "Detect Magic",
                            "Flare",
                            "Mage Hand",
                            "Message",
                            "Ray of Frost",
                            "Read Magic",
                            "Touch Of Fatigue"
                        ]
                    ]
                }
            ]
        },
        "statistics": {
            "abilities": {
                "str": 10,
                "dex": 14,
                "con": 12,
                "int": 22,
                "wis": 20,
                "cha": 18
            },
            "bab": 2,
            "languages": [
                "Common",
                "Dwarven",
                "Elven",
                "Gnome",
                "Goblin",
                "Halfling",
                "Orc"
            ],
            "feats": [],
            "traits": []
        },
        "skills": {
            "Acrobatics": {},
            "Appraise": {
                "ranks": 2,
                "classSkill": true,
                "other": [
                    "Raven Familiar||+3"
                ]
            },
            "Bluff": {},
            "Climb": {},
            "Craft (Clockwork)": {
                "classSkill": true,
                "ranks": 2
            },
            "Craft": {
                "skill": true
            },
            "Diplomacy": {
                "skill": true
            },
            "Disguise": {},
            "Escape Artist": {},
            "Fly": {
                "classSkill": true,
                "ranks": 5
            },
            "Heal": {},
            "Intimidate": {},
            "Knowledge (Arcana)": {
                "classSkill": true,
                "ranks": 5
            },
            "Knowledge (Dungeoneering)": {
                "classSkill": true,
                "ranks": 5
            },
            "Knowledge (Engineering)": {
                "classSkill": true,
                "ranks": 1
            },
            "Knowledge (Geography)": {
                "classSkill": true,
                "ranks": 1
            },
            "Knowledge (History)": {
                "classSkill": true,
                "ranks": 1
            },
            "Knowledge (Local)": {
                "classSkill": true,
                "ranks": 1
            },
            "Knowledge (Nature)": {
                "classSkill": true,
                "ranks": 1
            },
            "Knowledge (Nobility)": {
                "classSkill": true,
                "ranks": 1
            },
            "Knowledge (Planes)": {
                "classSkill": true,
                "ranks": 5
            },
            "Knowledge (Religion)": {
                "classSkill": true,
                "ranks": 5
            },
            "Perception": {
                "classSkill": true,
                "ranks": 5,
                "other": [
                    "Eyes and Ears of the City||+1",
                    "Alertness||+2"
                ]
            },
            "Perform": {},
            "Ride": {},
            "Sense Motive": {
                "other": [
                    "Alertness||+2"
                ]
            },
            "Spellcraft": {
                "classSkill": true,
                "ranks": 5
            },
            "Stealth": {},
            "Survival": {},
            "Swim": {}
        },
        "equipment": {
            "combat": [],
            "other": []
        },
        "special": []
    }
]